ccxt_tool_strands/__init__.py
ccxt_tool_strands/ccxt_generic.py
ccxt_tool_strands/ccxt_pro.py
ccxt_tool_strands-0.1.10.dist-info/METADATA
ccxt_tool_strands-0.1.10.dist-info/WHEEL
ccxt_tool_strands-0.1.10.dist-info/top_level.txt
ccxt_tool_strands-0.1.10.dist-info/RECORD
