Metadata-Version: 2.4
Name: ccxt-tool-strands
Version: 0.1.10
Summary: CCXT / CCXT Pro tools for Strands Agents
Author: macmert
License: MIT
Project-URL: Homepage, https://github.com/mertozbas/ccxt-tool-strands
Project-URL: Repository, https://github.com/mertozbas/ccxt-tool-strands
Keywords: ccxt,ccxtpro,strands,trading,tools
Classifier: Programming Language :: Python :: 3
Classifier: License :: OSI Approved :: MIT License
Classifier: Operating System :: OS Independent
Requires-Python: >=3.10
Requires-Dist: ccxt>=4.0.0
Requires-Dist: strands-agents>=1.17.0
